lwpipe/__init__.py
lwpipe/io.py
lwpipe/utils.py
tests/__init__.py
tests/test_node.py
tests/test_pipeline.py
lwpipe-5.1.1.dist-info/LICENSE
lwpipe-5.1.1.dist-info/METADATA
lwpipe-5.1.1.dist-info/WHEEL
lwpipe-5.1.1.dist-info/top_level.txt
lwpipe-5.1.1.dist-info/RECORD
