Metadata-Version: 2.1
Name: lwpipe
Version: 5.1.1
Summary: lightweight pipeline for numerical experiments
Home-page: https://github.com/estshorter/lwpipe
Author: estshorter
License: UNKNOWN
Platform: UNKNOWN
Classifier: License :: OSI Approved :: Apache Software License
Classifier: Programming Language :: Python :: 3.7
Classifier: Programming Language :: Python :: 3.8
Classifier: Programming Language :: Python :: 3.9
License-File: LICENSE
Provides-Extra: develop
Requires-Dist: pytest ; extra == 'develop'
Requires-Dist: numpy ; extra == 'develop'
Requires-Dist: pandas ; extra == 'develop'
